CHANGES.txt
MANIFEST.in
README.txt
setup.py
src/.DS_Store
src/z3c/.DS_Store
src/z3c/__init__.py
src/z3c.formwidget.bootstrap_datepicker.egg-info/PKG-INFO
src/z3c.formwidget.bootstrap_datepicker.egg-info/SOURCES.txt
src/z3c.formwidget.bootstrap_datepicker.egg-info/dependency_links.txt
src/z3c.formwidget.bootstrap_datepicker.egg-info/entry_points.txt
src/z3c.formwidget.bootstrap_datepicker.egg-info/namespace_packages.txt
src/z3c.formwidget.bootstrap_datepicker.egg-info/not-zip-safe
src/z3c.formwidget.bootstrap_datepicker.egg-info/requires.txt
src/z3c.formwidget.bootstrap_datepicker.egg-info/top_level.txt
src/z3c/formwidget/.DS_Store
src/z3c/formwidget/__init__.py
src/z3c/formwidget/bootstrap_datepicker/.DS_Store
src/z3c/formwidget/bootstrap_datepicker/__init__.py
src/z3c/formwidget/bootstrap_datepicker/configure.zcml
src/z3c/formwidget/bootstrap_datepicker/display.pt
src/z3c/formwidget/bootstrap_datepicker/fanstaticlibs.py
src/z3c/formwidget/bootstrap_datepicker/input.pt
src/z3c/formwidget/bootstrap_datepicker/input_component.pt
src/z3c/formwidget/bootstrap_datepicker/interfaces.py
src/z3c/formwidget/bootstrap_datepicker/widget.py
src/z3c/formwidget/bootstrap_datepicker/resources/.DS_Store
src/z3c/formwidget/bootstrap_datepicker/resources/bootstrap-datepicker.css
src/z3c/formwidget/bootstrap_datepicker/resources/bootstrap-datepicker.js
src/z3c/formwidget/bootstrap_datepicker/resources/bootstrap-datepicker.min.css
src/z3c/formwidget/bootstrap_datepicker/resources/bootstrap-datepicker.min.js
src/z3c/formwidget/bootstrap_datepicker/resources/locales/bootstrap-datepicker.bg.js
src/z3c/formwidget/bootstrap_datepicker/resources/locales/bootstrap-datepicker.bg.min.js
src/z3c/formwidget/bootstrap_datepicker/resources/locales/bootstrap-datepicker.ca.js
src/z3c/formwidget/bootstrap_datepicker/resources/locales/bootstrap-datepicker.ca.min.js
src/z3c/formwidget/bootstrap_datepicker/resources/locales/bootstrap-datepicker.cs.js
src/z3c/formwidget/bootstrap_datepicker/resources/locales/bootstrap-datepicker.cs.min.js
src/z3c/formwidget/bootstrap_datepicker/resources/locales/bootstrap-datepicker.da.js
src/z3c/formwidget/bootstrap_datepicker/resources/locales/bootstrap-datepicker.da.min.js
src/z3c/formwidget/bootstrap_datepicker/resources/locales/bootstrap-datepicker.de.js
src/z3c/formwidget/bootstrap_datepicker/resources/locales/bootstrap-datepicker.de.min.js
src/z3c/formwidget/bootstrap_datepicker/resources/locales/bootstrap-datepicker.el.js
