Metadata-Version: 1.0
Name: z3c.formwidget.bootstrap-datepicker
Version: 0.1
Summary: A twitter bootstrap datepicker widget for z3c.form.
Home-page: https://github.com/tmassman/z3c.formwidget.bootstrap_datepicker
Author: Thomas Massmann
Author-email: thomas.massmann@it-spir.it
License: GPL
Download-URL: http://pypi.python.org/pypi/z3c.formwidget.bootstrap_datepicker
Keywords: zope zope3 z3c.form
Platform: UNKNOWN
Classifier: Development Status :: 4 - Beta
Classifier: Environment :: Web Environment
Classifier: Framework :: Zope3
Classifier: Intended Audience :: Other Audience
Classifier: License :: OSI Approved :: GNU General Public License (GPL)
Classifier: Natural Language :: English
Classifier: Operating System :: OS Independent
Classifier: Programming Language :: Python
Classifier: Programming Language :: Zope
